baidu_apollo_proto/proto_v7/__init__.py
baidu_apollo_proto/proto_v7/__init__.pyi
baidu_apollo_proto/proto_v7/modules/__init__.py
baidu_apollo_proto/proto_v7/modules/__init__.pyi
baidu_apollo_proto/proto_v7/modules/audio/__init__.py
baidu_apollo_proto/proto_v7/modules/audio/__init__.pyi
baidu_apollo_proto/proto_v7/modules/audio/proto/__init__.py
baidu_apollo_proto/proto_v7/modules/audio/proto/__init__.pyi
baidu_apollo_proto/proto_v7/modules/audio/proto/audio_common_pb2.py
baidu_apollo_proto/proto_v7/modules/audio/proto/audio_conf_pb2.py
baidu_apollo_proto/proto_v7/modules/audio/proto/audio_event_pb2.py
baidu_apollo_proto/proto_v7/modules/audio/proto/audio_pb2.py
baidu_apollo_proto/proto_v7/modules/bridge/__init__.py
baidu_apollo_proto/proto_v7/modules/bridge/__init__.pyi
baidu_apollo_proto/proto_v7/modules/bridge/proto/__init__.py
baidu_apollo_proto/proto_v7/modules/bridge/proto/__init__.pyi
baidu_apollo_proto/proto_v7/modules/bridge/proto/udp_bridge_remote_info_pb2.py
baidu_apollo_proto/proto_v7/modules/canbus/__init__.py
baidu_apollo_proto/proto_v7/modules/canbus/__init__.pyi
baidu_apollo_proto/proto_v7/modules/canbus/proto/__init__.py
baidu_apollo_proto/proto_v7/modules/canbus/proto/__init__.pyi
baidu_apollo_proto/proto_v7/modules/canbus/proto/canbus_conf_pb2.py
baidu_apollo_proto/proto_v7/modules/canbus/proto/ch_pb2.py
baidu_apollo_proto/proto_v7/modules/canbus/proto/chassis_detail_pb2.py
baidu_apollo_proto/proto_v7/modules/canbus/proto/chassis_pb2.py
baidu_apollo_proto/proto_v7/modules/canbus/proto/devkit_pb2.py
baidu_apollo_proto/proto_v7/modules/canbus/proto/ge3_pb2.py
baidu_apollo_proto/proto_v7/modules/canbus/proto/lexus_pb2.py
baidu_apollo_proto/proto_v7/modules/canbus/proto/neolix_edu_pb2.py
baidu_apollo_proto/proto_v7/modules/canbus/proto/transit_pb2.py
baidu_apollo_proto/proto_v7/modules/canbus/proto/vehicle_parameter_pb2.py
baidu_apollo_proto/proto_v7/modules/canbus/proto/wey_pb2.py
baidu_apollo_proto/proto_v7/modules/canbus/proto/zhongyun_pb2.py
baidu_apollo_proto-0.1.1.dist-info/METADATA
baidu_apollo_proto-0.1.1.dist-info/WHEEL
baidu_apollo_proto-0.1.1.dist-info/RECORD
