Metadata-Version: 2.1
Name: baidu-apollo-proto
Version: 0.1.1
Summary: Compiled protobuff used in Baidu Apollo for Python.
Author: Yuqi Huai
Author-email: yhuai@uci.edu
Requires-Python: >=3.10
Classifier: Programming Language :: Python :: 3
Classifier: Programming Language :: Python :: 3.10
Classifier: Programming Language :: Python :: 3.11
Classifier: Programming Language :: Python :: 3.12
Requires-Dist: protobuf (==3.19.5)
